MANIFEST.in
README.md
setup.py
tf_object_detection_util/__init__.py
tf_object_detection_util.egg-info/PKG-INFO
tf_object_detection_util.egg-info/SOURCES.txt
tf_object_detection_util.egg-info/dependency_links.txt
tf_object_detection_util.egg-info/not-zip-safe
tf_object_detection_util.egg-info/requires.txt
tf_object_detection_util.egg-info/top_level.txt
tf_object_detection_util/inference_api/__init__.py
tf_object_detection_util/inference_api/util.py
tf_object_detection_util/training_api/__init__.py
tf_object_detection_util/training_api/generate_tfrecord.py
tf_object_detection_util/training_api/util.py
tf_object_detection_util/training_api/configs/faster_rcnn_open_images.config
tf_object_detection_util/training_api/configs/mobilenet_fpn_coco.config
tf_object_detection_util/training_api/configs/ssd_mobilenet_v1_pets.config
tf_object_detection_util/training_api/configs/ssd_resnet_50_fpn_coco.config