Metadata-Version: 1.0
Name: tf-object-detection-util
Version: 0.1.8
Summary: A library to make Object Detection using Tensorflow Object Detection API easier.
Home-page: https://github.com/prasannals/tf_object_detection_util
Author: Prasanna Lakkur Subramanyam
Author-email: prasanna.lakkur@gmail.com
License: MIT
Platform: UNKNOWN
